logsift/__main__.py
logsift/args.py
logsift/bindings.py
logsift/filtering.py
logsift/log.py
logsift/log_collection.py
logsift/term_decoder.py
logsift/components/documentation.py
logsift/components/spacer.py
logsift/components/title.py
logsift/css/app.tcss
logsift/docs/docs.md
logsift/types/ids.py
logsift-1.1.1.dist-info/METADATA
logsift-1.1.1.dist-info/WHEEL
logsift-1.1.1.dist-info/RECORD
